tests/__init__.py
tests/test_categorical_encoding.py
tests/test_data_reading.py
tests/test_data_summary.py
tests/test_missing_values.py
DataPrepKitHussen-0.1.dist-info/METADATA
DataPrepKitHussen-0.1.dist-info/WHEEL
DataPrepKitHussen-0.1.dist-info/top_level.txt
DataPrepKitHussen-0.1.dist-info/RECORD
