Metadata-Version: 2.1
Name: DataPrepKitHussen
Version: 0.1
Summary: A data preparation toolkit
Author: Hussen
Requires-Dist: pandas
Requires-Dist: numpy
Requires-Dist: sklearn
